LICENSE.txt
README.md
setup.py
RandomPassword/Exceptions.py
RandomPassword/__init__.py
RandomPassword.egg-info/PKG-INFO
RandomPassword.egg-info/SOURCES.txt
RandomPassword.egg-info/dependency_links.txt
RandomPassword.egg-info/top_level.txt