Metadata-Version: 2.1
Name: RandomPassword
Version: 1.0
Summary: A simple python library to generate customizable random passwords in python!
Home-page: https://github.com/Sid72020123/RandomPassword
Author: Siddhesh Chavan
Author-email: siddheshchavan2020@gmail.com
License: MIT
Keywords: random-passsword password random
Platform: UNKNOWN
Classifier: Development Status :: 5 - Production/Stable
Classifier: Intended Audience :: Education
Classifier: Operating System :: Microsoft :: Windows :: Windows 10
Classifier: License :: OSI Approved :: MIT License
Classifier: Programming Language :: Python :: 3
